auto_py_to_app/__init__.py
auto_py_to_app/__main__.py
auto_py_to_app/config.py
auto_py_to_app/dialogs.py
auto_py_to_app/log.py
auto_py_to_app/packaging.py
auto_py_to_app/ui.py
auto_py_to_app/utils.py
auto_py_to_app/validation.py
auto_py_to_app/web/GitHub_Logo_Black.png
auto_py_to_app/web/Github_Logo_White.png
auto_py_to_app/web/Nunito-Light.ttf
auto_py_to_app/web/favicon.ico
auto_py_to_app/web/index.html
auto_py_to_app/web/.idea/.gitignore
auto_py_to_app/web/.idea/modules.xml
auto_py_to_app/web/.idea/vcs.xml
auto_py_to_app/web/.idea/web.iml
auto_py_to_app/web/css/general.css
auto_py_to_app/web/css/main.css
auto_py_to_app/web/css/modal.css
auto_py_to_app/web/img/chevron-square-up.svg
auto_py_to_app/web/img/moon.svg
auto_py_to_app/web/img/plus.svg
auto_py_to_app/web/img/remove.svg
auto_py_to_app/web/img/sun.svg
auto_py_to_app/web/js/configuration.js
auto_py_to_app/web/js/constants.js
auto_py_to_app/web/js/i18n.js
auto_py_to_app/web/js/importExport.js
auto_py_to_app/web/js/initialise.js
auto_py_to_app/web/js/interface.js
auto_py_to_app/web/js/messages.js
auto_py_to_app/web/js/modal.js
auto_py_to_app/web/js/packaging.js
auto_py_to_app/web/js/staticEvents.js
auto_py_to_app/web/js/utils.js
auto_py_to_app-0.0.7.dist-info/licenses/LICENSE
auto_py_to_app-0.0.7.dist-info/METADATA
auto_py_to_app-0.0.7.dist-info/WHEEL
auto_py_to_app-0.0.7.dist-info/entry_points.txt
auto_py_to_app-0.0.7.dist-info/top_level.txt
auto_py_to_app-0.0.7.dist-info/RECORD
