Metadata-Version: 2.4
Name: auto-py-to-app
Version: 0.0.7
Summary: auto-py-to-app is a cx-Freeze GUI to package .py into .exe or excutable files.
Home-page: https://auto-py-to-app-doc.readthedocs.io/zh/latest/
Author: Syuya_Murakami
Author-email: wxy135@mail.ustc.edu.cn
Project-URL: Bug Tracker, https://auto-py-to-app-doc.readthedocs.io/zh/latest/
Keywords: gui,executable
Classifier: Programming Language :: Python :: 3
Classifier: License :: OSI Approved :: MIT License
Classifier: Operating System :: OS Independent
Requires-Python: >=3.9
License-File: LICENSE
Requires-Dist: Eel==0.14.0
Requires-Dist: cx-Freeze>=6.15.0
Dynamic: author
Dynamic: author-email
Dynamic: classifier
Dynamic: description
Dynamic: description-content-type
Dynamic: home-page
Dynamic: keywords
Dynamic: license-file
Dynamic: project-url
Dynamic: requires-dist
Dynamic: requires-python
Dynamic: summary
